<?xml version="1.0" encoding="utf-8" ?>
<manifest>
  <control 
    namespace="Sample" 
    constructor="GoogleMapsGrid" 
    version="0.0.2" 
    display-name-key="GoogleMapsGrid_Display_Key" 
    description-key="GoogleMapsGrid_Desc_Key" 
    control-type="standard">
    <data-set 
        name="mapDataSet" 
        display-name-key="mapDataSet_Display_Key">
      <property-set 
        name="latitude" 
        display-name-key="MapGrid_latField_Display_Key" 
        description-key="MapGrid_latField_Desc_Key" 
        of-type="FP" 
        usage="bound" 
        required="true" />
      <property-set 
        name="longitude" 
        display-name-key="MapGrid_longField_Display_Key" 
        description-key="MapGrid_longField_Desc_Key" 
        of-type="FP" 
        usage="bound" 
        required="true" />
      <property-set 
        name="name" 
        display-name-key="MapGrid_primaryField_Display_Key" 
        description-key="MapGrid_primaryField_Desc_Key" 
        of-type="SingleLine.Text" 
        usage="bound" 
        required="true" />
    </data-set>
    <property name="googleMapsAPIKey" display-name-key="MapGrid_googleMapsAPIKey_Display_Key" description-key="MapGrid_googleMapsAPIKey_Desc_Key" of-type="SingleLine.Text" usage="input" required="true"  />
    <resources>
      <code path="index.ts" order="1"/>
      <css path="css/GoogleMapsGrid.css" order="1" />
      <resx path="strings/GoogleMapsGrid.1033.resx" version="1.0.0" />
    </resources>
  </control>
</manifest>
